hfradarpy/__init__.py
hfradarpy/__main__.py
hfradarpy/_version.py
hfradarpy/calc.py
hfradarpy/cli.py
hfradarpy/common.py
hfradarpy/ctf.py
hfradarpy/radials.py
hfradarpy/waves.py
hfradarpy/io/__init__.py
hfradarpy/io/nc.py
hfradarpy/plot/__init__.py
hfradarpy/plot/common.py
hfradarpy/plot/plot_nc.py
hfradarpy/plot/plot_ruv.py
hfradarpy/plot/quiver_plot.py
hfradarpy-0.1.5.dist-info/AUTHORS.rst
hfradarpy-0.1.5.dist-info/LICENSE
hfradarpy-0.1.5.dist-info/METADATA
hfradarpy-0.1.5.dist-info/WHEEL
hfradarpy-0.1.5.dist-info/entry_points.txt
hfradarpy-0.1.5.dist-info/top_level.txt
hfradarpy-0.1.5.dist-info/RECORD
