Metadata-Version: 2.1
Name: hfradarpy
Version: 0.1.5
Summary: Toolbox to read in High Frequency Radar (HFR) files written in CODAR Tabular Format (CTF).
Home-page: https://github.com/rucool/hfradarpy
Author: Michael Smith
Author-email: michaesm@marine.rutgers.edu
License: MIT license
Keywords: hfradarpy
Platform: UNKNOWN
Classifier: Development Status :: 2 - Pre-Alpha
Classifier: Intended Audience :: Developers
Classifier: License :: OSI Approved :: MIT License
Classifier: Natural Language :: English
Classifier: Programming Language :: Python :: 3.7
Classifier: Programming Language :: Python :: 3.8
Classifier: Programming Language :: Python :: 3.9
Classifier: Programming Language :: Python :: 3.10
Requires-Python: >=3.7
License-File: LICENSE
License-File: AUTHORS.rst
Requires-Dist: xarray
Requires-Dist: netcdf4
Requires-Dist: pyproj
Requires-Dist: click
